fds/__init__.py
fds/sdk/__init__.py
fds/sdk/RealTimeQuotes/__init__.py
fds/sdk/RealTimeQuotes/api_client.py
fds/sdk/RealTimeQuotes/configuration.py
fds/sdk/RealTimeQuotes/exceptions.py
fds/sdk/RealTimeQuotes/model_utils.py
fds/sdk/RealTimeQuotes/rest.py
fds/sdk/RealTimeQuotes/api/__init__.py
fds/sdk/RealTimeQuotes/api/basic_api.py
fds/sdk/RealTimeQuotes/api/category_api.py
fds/sdk/RealTimeQuotes/api/instrument_api.py
fds/sdk/RealTimeQuotes/api/notation_api.py
fds/sdk/RealTimeQuotes/api/prices_api.py
fds/sdk/RealTimeQuotes/apis/__init__.py
fds/sdk/RealTimeQuotes/model/__init__.py
fds/sdk/RealTimeQuotes/model/attributes_member.py
fds/sdk/RealTimeQuotes/model/cursor_based_pagination_output_object.py
fds/sdk/RealTimeQuotes/model/cursor_based_pagination_output_object_without_total.py
fds/sdk/RealTimeQuotes/model/error_meta_object.py
fds/sdk/RealTimeQuotes/model/error_object.py
fds/sdk/RealTimeQuotes/model/inline_response200.py
fds/sdk/RealTimeQuotes/model/inline_response2001.py
fds/sdk/RealTimeQuotes/model/inline_response20010.py
fds/sdk/RealTimeQuotes/model/inline_response20010_data.py
fds/sdk/RealTimeQuotes/model/inline_response20011.py
fds/sdk/RealTimeQuotes/model/inline_response20011_data.py
fds/sdk/RealTimeQuotes/model/inline_response20012.py
fds/sdk/RealTimeQuotes/model/inline_response20012_data.py
fds/sdk/RealTimeQuotes/model/inline_response20013.py
fds/sdk/RealTimeQuotes/model/inline_response20013_data.py
fds/sdk/RealTimeQuotes/model/inline_response20013_kind.py
fds/sdk/RealTimeQuotes/model/inline_response20014.py
fds/sdk/RealTimeQuotes/model/inline_response20014_data.py
fds/sdk/RealTimeQuotes/model/inline_response20015.py
fds/sdk/RealTimeQuotes/model/inline_response20015_data.py
fds/sdk/RealTimeQuotes/model/inline_response20015_data_nested_regions.py
fds/sdk/RealTimeQuotes/model/inline_response20016.py
fds/sdk/RealTimeQuotes/model/inline_response20016_data.py
fds/sdk/RealTimeQuotes/model/inline_response20017.py
fds.sdk.RealTimeQuotes-0.12.5.dist-info/LICENSE
fds.sdk.RealTimeQuotes-0.12.5.dist-info/METADATA
fds.sdk.RealTimeQuotes-0.12.5.dist-info/WHEEL
fds.sdk.RealTimeQuotes-0.12.5.dist-info/top_level.txt
fds.sdk.RealTimeQuotes-0.12.5.dist-info/RECORD
